dwarf_debugger/__init__.py
dwarf_debugger/color.py
dwarf_debugger/creator.py
dwarf_debugger/dwarf.py
dwarf_debugger/injector.py
dwarf_debugger/resources.py
dwarf_debugger/strace.py
dwarf_debugger/trace.py
dwarf_debugger/version.py
dwarf_debugger/assets/Anton-OFL.txt
dwarf_debugger/assets/Anton.ttf
dwarf_debugger/assets/OpenSans-Bold.ttf
dwarf_debugger/assets/OpenSans-LICENSE.txt
dwarf_debugger/assets/OpenSans-Regular.ttf
dwarf_debugger/assets/android.png
dwarf_debugger/assets/android.svg
dwarf_debugger/assets/apple.png
dwarf_debugger/assets/apple.svg
dwarf_debugger/assets/black_style.qss
dwarf_debugger/assets/branch_closed.svg
dwarf_debugger/assets/branch_open.svg
dwarf_debugger/assets/close_btn.png
dwarf_debugger/assets/close_btn_h.png
dwarf_debugger/assets/dark_style.qss
dwarf_debugger/assets/dwarf.ico
dwarf_debugger/assets/dwarf.png
dwarf_debugger/assets/dwarf.svg
dwarf_debugger/assets/dwarf_alpha.png
dwarf_debugger/assets/expand.png
dwarf_debugger/assets/expand_l.png
dwarf_debugger/assets/light_style.qss
dwarf_debugger/assets/local.png
dwarf_debugger/assets/local.svg
dwarf_debugger/assets/remote.png
dwarf_debugger/assets/remote.svg
dwarf_debugger/assets/style.qss
dwarf_debugger/assets/icons/check.svg
dwarf_debugger/assets/icons/dash.svg
dwarf_debugger/assets/icons/divider_h.svg
dwarf_debugger/assets/icons/divider_v.svg
dwarf_debugger/assets/icons/issue.svg
dwarf_debugger/assets/icons/license.txt
dwarf_debugger/assets/icons/pause.png
dwarf_debugger/assets/icons/plus.svg
dwarf_debugger/assets/icons/primitive-dot.svg
dwarf_debugger/assets/icons/record.png
dwarf_debugger/assets/icons/stop.png
dwarf_debugger/assets/icons/trashcan.svg
dwarf_debugger/assets/icons/undock.svg
dwarf_debugger/assets/icons/x.svg
dwarf_debugger/lib/__init__.py
dwarf_debugger/lib/adb.py
dwarf_debugger/lib/android.py
dwarf_debugger/lib/context.py
dwarf_debugger/lib/core.js
dwarf_debugger/lib/core.py
dwarf_debugger/lib/database.py
dwarf_debugger/lib/disassembler.py
dwarf_debugger-1.1.3.dist-info/LICENSE
dwarf_debugger-1.1.3.dist-info/METADATA
dwarf_debugger-1.1.3.dist-info/WHEEL
dwarf_debugger-1.1.3.dist-info/entry_points.txt
dwarf_debugger-1.1.3.dist-info/top_level.txt
dwarf_debugger-1.1.3.dist-info/RECORD
