Metadata-Version: 2.1
Name: dwarf-debugger
Version: 1.1.3
Summary: Full featured multi arch/os debugger built on top of PyQt5 and frida
Home-page: https://github.com/iGio90/Dwarf
Author: Giovanni Rocca (iGio90)
Author-email: giovanni.rocca.90@gmail.com
License: GPLv3+
Platform: UNKNOWN
Classifier: Development Status :: 4 - Beta
Classifier: Programming Language :: Python :: 3
Classifier: Operating System :: OS Independent
Classifier: Operating System :: POSIX
Classifier: Operating System :: Microsoft :: Windows
Classifier: Operating System :: MacOS :: MacOS X
Classifier: Intended Audience :: Developers
Classifier: Intended Audience :: Education
Classifier: Intended Audience :: Science/Research
Classifier: Topic :: Software Development :: Debuggers
Classifier: Topic :: Software Development :: Disassemblers
Classifier: Topic :: Security
Requires-Python: >=3
License-File: LICENSE
Requires-Dist: capstone (>=4.0.1)
Requires-Dist: requests (>=2.22.0)
Requires-Dist: frida (>=12.8.0)
Requires-Dist: PyQt5 (>=5.11.3)
Requires-Dist: pyperclip (>=1.7.0)
